{"cicada-引擎-2.0-发布了":{"title":"Cicada 引擎 2.0 发布了","description":"基础教程","author":"imink","date":"2017-06-30T00:00:00.000Z","url":"cicada-引擎-2.0-发布了","toc":[],"content":"<p>\b安装之前确保系统已经安装了最新的 Node.js 以及 NPM，如果你还没有安装，请前往<a href=\"\">这里</a>。</p>\n<p>接下来，</p>\n<p><code>npm install --save @cicada/render</code></p>\n<p>安装核心的引擎模块。你就可以写一些简单的程序了。因为 Cicada 应用于\b React Lego 组件，你可以来<a href=\"\">这里</a> 找到我们提供的 antd UI 组件，或者也可以按照 <a href=\"\">React Lego 规范</a> 来根据需求编写组件。</p>\n<p>在 example 文件夹当中，我们提供了常见的 demo（其中包含了常见的场景，比如表单验证和路由\b用法）方便快速上手。</p>\n"}}